README.md
setup.cfg
setup.py
jslfirebaseutil.egg-info/PKG-INFO
jslfirebaseutil.egg-info/SOURCES.txt
jslfirebaseutil.egg-info/dependency_links.txt
jslfirebaseutil.egg-info/requires.txt
jslfirebaseutil.egg-info/top_level.txt
jslfirebaseutils/__init__.py
jslfirebaseutils/main.py
jslfirebaseutils/cloudstore/__init__.py
jslfirebaseutils/cloudstore/cloud_store_utils.py