Metadata-Version: 2.1
Name: jslfirebaseutil
Version: 1.0.7
Summary: JSoftwareLabs Utils for Firebase
Home-page: https://github.com/JSoftwareLabs/JSLFireBaseUtils
Author: JSoftwareLabs.com
Author-email: info@jsoftwarelabs.com
License: MIT
Download-URL: https://github.com/JSoftwareLabs/JSLFireBaseUtils/archive/refs/tags/V1_0_7.tar.gz
Keywords: Firebase,JSoftwareLabs,Cloudstore,Firestore,Firebase Utility
Platform: UNKNOWN
Classifier: Development Status :: 4 - Beta
Classifier: Intended Audience :: Developers
Classifier: Topic :: Software Development :: Build Tools
Classifier: License :: OSI Approved :: Apache Software License
Classifier: Programming Language :: Python :: 3.5
Classifier: Programming Language :: Python :: 3.6
Classifier: Programming Language :: Python :: 3.7
Classifier: Programming Language :: Python :: 3.8
Classifier: Programming Language :: Python :: 3.9
